Chrones/__init__.py
Chrones/__main__.py
Chrones/command_line_interface.py
Chrones/instrumentation/__init__.py
Chrones/instrumentation/shell.py
Chrones/instrumentation/cpp/__init__.py
Chrones/instrumentation/cpp/chrones.hpp
Chrones/monitoring/__init__.py
Chrones/monitoring/result.py
Chrones/monitoring/runner.py
Chrones/reporting/__init__.py
Chrones/reporting/graph.py
Chrones/reporting/summaries.py
Chrones-1.1.1.dist-info/LICENSE
Chrones-1.1.1.dist-info/METADATA
Chrones-1.1.1.dist-info/WHEEL
Chrones-1.1.1.dist-info/entry_points.txt
Chrones-1.1.1.dist-info/top_level.txt
Chrones-1.1.1.dist-info/RECORD
