Metadata-Version: 2.1
Name: Chrones
Version: 1.1.1
Summary: Software development tool to visualize runtime statistics about your program and correlate them with its phases
Home-page: https://github.com/jacquev6/Chrones
Author: Vincent Jacques
Author-email: vincent@vincent-jacques.net
License: MIT
License-File: LICENSE
Requires-Dist: click
Requires-Dist: dacite
Requires-Dist: matplotlib
Requires-Dist: psutil
